Workbook

Sheet Summary
A1: PhotoCraft Codebase Cartography Audit: Key Numbers
A2: Commit 366002f, measured 2026-10-14. Each value links to the sheet it comes from.
A4: Metric | B4: Value
A5: System LOC | B5: ='LOC Summary'!B4 -> 257637
A6: DevOps/Test LOC | B6: ='LOC Summary'!B5 -> 205552
A7: Total authored LOC | B7: ='LOC Summary'!B6 -> 463189
A8: System cyclomatic complexity | B8: ='LOC Summary'!G4 -> 61232
A9: System function points (IFPUG AFP) | B9: ='Function Points'!B32 -> 3899
A10: Backfired System FP | B10: ='Function Points'!B33 -> 3605
A11: Total FP (System + DevOps/Test) | B11: ='Function Points'!C41 -> 6780
A12: Headline cost, low (0.32 FP/day) | B12: =Cost!B20 -> 9046487
A13: Headline cost, high (0.32 FP/day) | B13: =Cost!C20 -> 10554235
A14: Tests | B14: ='Test Pyramid'!C7 -> 8472
A15: Clippy warnings | B15: =Clippy!B77 -> 25244

Sheet Languages
A1: Language breakdown (scc 3.5.0, whole repo)
A3: Language | B3: Files | C3: Lines | D3: Blanks | E3: Comments | F3: Code | G3: Complexity
A4: Rust | B4: 1306 | C4: 539017 | D4: 31242 | E4: 50788 | F4: 456987 | G4: 73021
A5: SVG | B5: 151 | C5: 2246 | D5: 5 | E5: 14 | F5: 2227 | G5: 0
A6: Markdown | B6: 102 | C6: 10752 | D6: 1968 | E6: 0 | F6: 8784 | G6: 0
A7: TOML | B7: 52 | C7: 3285 | D7: 363 | E7: 218 | F7: 2704 | G7: 26
A8: Shell | B8: 16 | C8: 1291 | D8: 104 | E8: 254 | F8: 933 | G8: 190
A9: Plain Text | B9: 12 | C9: 1159 | D9: 199 | E9: 0 | F9: 960 | G9: 0
A10: YAML | B10: 11 | C10: 795 | D10: 56 | E10: 142 | F10: 597 | G10: 0
A11: JSON | B11: 4 | C11: 3801 | D11: 0 | E11: 0 | F11: 3801 | G11: 0
A12: Powershell | B12: 3 | C12: 322 | D12: 11 | E12: 54 | F12: 257 | G12: 35
A13: Autoconf | B13: 2 | C13: 311 | D13: 2 | E13: 0 | F13: 309 | G13: 1
A14: License | B14: 2 | C14: 198 | D14: 31 | E14: 0 | F14: 167 | G14: 0
A15: Python | B15: 2 | C15: 275 | D15: 18 | E15: 47 | F15: 210 | G15: 21
... A20: XML | B20: 1 | C20: 35 | D20: 0 | E20: 2 | F20: 33 | G20: 0
A21: Total | B21: =SUM(B4:B20) -> 1668 | C21: =SUM(C4:C20) -> 564966 | D21: =SUM(D4:D20) -> 34088 | E21: =SUM(E4:E20) -> 51677 | F21: =SUM(F4:F20) -> 479201 | G21: =SUM(G4:G20) -> 73615

Sheet LOC Summary
A1: Lines of code: System / DevOps-Test / Total
A3: Category | B3: LOC | C3: Share of authored | D3: Files | E3: Types | F3: Fns | G3: CC
A4: System | B4: 257637 | C4: 0.556 | D4: 772 | E4: 1717 | F4: 13289 | G4: 61232
A5: DevOps/Test | B5: 205552 | C5: 0.444 | D5: 1113 | E5: 114 | F5: 11666 | G5: 27196
A6: Total (authored) | B6: =SUM(B4:B5) -> 463189 | C6: 1 | D6: =SUM(D4:D5) -> 1885 | E6: =SUM(E4:E5) -> 1831 | F6: =SUM(F4:F5) -> 24955 | G6: =SUM(G4:G5) -> 88428
A7: Excluded (non-code / generated) | B7: 16012 | C7: -

Sheet Components
A1: Per-component rollup (LOC, types, functions, cyclomatic complexity)
A2: Rust CC = extended McCabe; other languages = scc proxy. Subtotals are SUM formulas.
A4: Component | B4: Category | C4: Files | D4: LOC | E4: Types | F4: Fns | G4: CC | H4: CC/type | I4: CC/fn | J4: Density | K4: ? | L4: Hottest file (CC)
A5: crates/ui-egui | B5: System | C5: 229 | D5: 82376 | E5: 424 | F5: 4082 | G5: 20699 | H5: 48.8 | I5: 5.07 | J5: 0.251 | K5: 1463 | L5: crates/ui-egui/src/canvas.rs (1,434)
A6: crates/engine | B6: System | C6: 136 | D6: 56306 | E6: 210 | F6: 3059 | G6: 12308 | H6: 58.6 | I6: 4.02 | J6: 0.219 | K6: 4128 | L6: crates/engine/src/atn_cmds.rs (774)
A7: crates/algo | B7: System | C7: 107 | D7: 33115 | E7: 235 | F7: 1361 | G7: 7879 | H7: 33.5 | I7: 5.79 | J7: 0.238 | K7: 661 | L7: crates/algo/src/inpaint.rs (435)
A8: crates/io | B8: System | C8: 35 | D8: 13002 | E8: 51 | F8: 663 | G8: 3264 | H8: 64 | I8: 4.92 | J8: 0.251 | K8: 971 | L8: crates/io/src/psd_export.rs (394)
A9: crates/codecs | B9: System | C9: 36 | D9: 10325 | E9: 80 | F9: 489 | G9: 2563 | H9: 32 | I9: 5.24 | J9: 0.248 | K9: 696 | L9: crates/codecs/src/codecs/tiff.rs (306)
A10: crates/psd | B10: System | C10: 29 | D10: 7733 | E10: 93 | F10: 516 | G10: 1746 | H10: 18.8 | I10: 3.38 | J10: 0.226 | K10: 1082 | L10: crates/psd/src/tiff.rs (345)
A11: crates/raw | B11: System | C11: 26 | D11: 7173 | E11: 66 | F11: 323 | G11: 1682 | H11: 25.5 | I11: 5.21 | J11: 0.234 | K11: 293 | L11: crates/raw/src/testgen.rs (233)
A12: crates/text | B12: System | C12: 16 | D12: 5749 | E12: 55 | F12: 318 | G12: 1434 | H12: 26.1 | I12: 4.51 | J12: 0.249 | K12: 149 | L12: crates/text/src/layout.rs (287)
A13: crates/compose | B13: System | C13: 14 | D13: 5419 | E13: 32 | F13: 345 | G13: 1506 | H13: 47.1 | I13: 4.37 | J13: 0.278 | K13: 15 | L13: crates/compose/src/effects.rs (480)
A14: crates/gpu | B14: System | C14: 7 | D14: 5403 | E14: 39 | F14: 204 | G14: 1202 | H14: 30.8 | I14: 5.89 | J14: 0.222 | K14: 58 | L14: crates/gpu/src/plan.rs (340)
A15: crates/paint | B15: System | C15: 15 | D15: 4488 | E15: 53 | F15: 229 | G15: 943 | H15: 17.8 | I15: 4.12 | J15: 0.21 | K15: 6 | L15: crates/paint/src/render.rs (261)
A16: apps/photocraft | B16: System | C16: 24 | D16: 4022 | E16: 33 | F16: 232 | G16: 879 | H16: 26.6 | I16: 3.79 | J16: 0.219 | K16: 166 | L16: apps/photocraft/src/screen_color.rs (104)
... A31: crates/heif | B31: System | C31: 1 | D31: 112 | E31: 4 | F31: 9 | G31: 19 | H31: 4.8 | I31: 2.11 | J31: 0.17 | K31: 3 | L31: crates/heif/src/lib.rs (19)
A32: System subtotal | C32: =SUM(C5:C31) -> 772 | D32: =SUM(D5:D31) -> 257637 | E32: =SUM(E5:E31) -> 1717 | F32: =SUM(F5:F31) -> 13289 | G32: =SUM(G5:G31) -> 61232 | H32: 35.7 | I32: 4.61 | J32: 0.238 | K32: =SUM(K5:K31) -> 10707
A33: crates/ui-egui (tests) | B33: DevOps/Test | C33: 312 | D33: 75302 | E33: 33 | F33: 4278 | G33: 9061 | H33: 274.6 | I33: 2.12 | J33: 0.12 | K33: 229 | L33: crates/ui-egui/src/panels.rs (232)
A34: crates/engine (tests) | B34: DevOps/Test | C34: 198 | D34: 43983 | E34: 7 | F34: 2494 | G34: 5294 | H34: 756.3 | I34: 2.12 | J34: 0.12 | K34: 129 | L34: crates/engine/src/retouch_cmds/tests.rs (305)
A35: crates/io (tests) | B35: DevOps/Test | C35: 97 | D35: 15565 | E35: 8 | F35: 865 | G35: 2152 | H35: 269 | I35: 2.49 | J35: 0.138 | K35: 21 | L35: crates/io/tests/flat.rs (128)
A36: crates/algo (tests) | B36: DevOps/Test | C36: 89 | D36: 13127 | E36: 1 | F36: 694 | G36: 2645 | H36: 2645 | I36: 3.81 | J36: 0.201 | K36: 28 | L36: crates/algo/src/segment/tests.rs (146)
A37: crates/codecs (tests) | B37: DevOps/Test | C37: 51 | D37: 8121 | E37: 12 | F37: 623 | G37: 1510 | H37: 125.8 | I37: 2.42 | J37: 0.186 | K37: 10 | L37: crates/codecs/tests/deep_exr.rs (136)
A38: crates/psd (tests) | B38: DevOps/Test | C38: 48 | D38: 5981 | E38: 2 | F38: 419 | G38: 848 | H38: 424 | I38: 2.02 | J38: 0.142 | K38: 31 | L38: crates/psd/tests/swatch_malformed.rs (105)
A39: crates/compose (tests) | B39: DevOps/Test | C39: 18 | D39: 5402 | E39: 1 | F39: 347 | G39: 812 | H39: 812 | I39: 2.34 | J39: 0.15 | K39: 3 | L39: crates/compose/src/tests.rs (332)
A40: xtask | B40: DevOps/Test | C40: 12 | D40: 4393 | E40: 30 | F40: 232 | G40: 832 | H40: 27.7 | I40: 3.59 | J40: 0.189 | K40: 171 | L40: xtask/src/perf.rs (166)
A41: crates/raw (tests) | B41: DevOps/Test | C41: 31 | D41: 3681 | E41: 3 | F41: 235 | G41: 562 | H41: 187.3 | I41: 2.39 | J41: 0.153 | K41: 2 | L41: crates/raw/tests/dng.rs (84)
A42: crates/automation (tests) | B42: DevOps/Test | C42: 18 | D42: 3614 | E42: 4 | F42: 182 | G42: 362 | H42: 90.5 | I42: 1.99 | J42: 0.1 | K42: 2 | L42: crates/automation/tests/mcp.rs (125)
A43: crates/gpu (tests) | B43: DevOps/Test | C43: 10 | D43: 3281 | E43: 1 | F43: 139 | G43: 379 | H43: 379 | I43: 2.73 | J43: 0.116 | K43: 19 | L43: crates/gpu/tests/parity.rs (215)
A44: crates/text (tests) | B44: DevOps/Test | C44: 18 | D44: 3155 | E44: 0 | F44: 185 | G44: 424 | H44: 0 | I44: 2.29 | J44: 0.134 | K44: 0 | L44: crates/text/src/tests.rs (220)
... A72: devops: .cargo/ | B72: DevOps/Test | C72: 1 | D72: 2 | E72: 0 | F72: 0 | G72: 0 | H72: 0 | I72: 0 | J72: 0 | K72: 0 | L72: (0)
A73: DevOps/Test subtotal | C73: =SUM(C33:C72) -> 1113 | D73: =SUM(D33:D72) -> 205552 | E73: =SUM(E33:E72) -> 114 | F73: =SUM(F33:F72) -> 11666 | G73: =SUM(G33:G72) -> 27196 | H73: 238.6 | I73: 2.33 | J73: 0.132 | K73: =SUM(K33:K72) -> 687
A74: Excluded: Markdown | B74: Excluded | C74: 102 | D74: 8784 | E74: 0 | F74: 0 | G74: 0 | H74: 0 | I74: 0 | J74: 0 | K74: 0 | L74: (0)
A75: Excluded: JSON | B75: Excluded | C75: 4 | D75: 3801 | E75: 0 | F75: 0 | G75: 0 | H75: 0 | I75: 0 | J75: 0 | K75: 0 | L75: (0)
A76: Excluded: SVG | B76: Excluded | C76: 151 | D76: 2227 | E76: 0 | F76: 0 | G76: 0 | H76: 0 | I76: 0 | J76: 0 | K76: 0 | L76: (0)
A77: Excluded: Plain Text | B77: Excluded | C77: 12 | D77: 960 | E77: 0 | F77: 0 | G77: 0 | H77: 0 | I77: 0 | J77: 0 | K77: 0 | L77: (0)
A78: Excluded: License | B78: Excluded | C78: 2 | D78: 167 | E78: 0 | F78: 0 | G78: 0 | H78: 0 | I78: 0 | J78: 0 | K78: 0 | L78: (0)
A79: Excluded: generated Rust | B79: Excluded | C79: 1 | D79: 46 | E79: 1 | F79: 0 | G79: 1 | H79: 1 | I79: 0 | J79: 0.022 | K79: 0 | L79: crates/raw/src/tone/tables.rs (1)
A80: Excluded: book/ | B80: Excluded | C80: 1 | D80: 27 | E80: 0 | F80: 0 | G80: 0 | H80: 0 | I80: 0 | J80: 0 | K80: 0 | L80: (0)
A81: Excluded subtotal | C81: =SUM(C74:C80) -> 273 | D81: =SUM(D74:D80) -> 16012 | E81: =SUM(E74:E80) -> 1 | F81: =SUM(F74:F80) -> 0 | G81: =SUM(G74:G80) -> 1 | H81: 1 | I81: 0 | J81: 0 | K81: =SUM(K74:K80) -> 0
A82: GRAND TOTAL (System + DevOps/Test) | D82: 463189

Sheet LOC by Language
A1: LOC by category and language (backfiring input)
A3: Category | B3: Language | C3: LOC
A4: DevOps/Test | B4: Autoconf | C4: 309
A5: DevOps/Test | B5: Docker ignore | C5: 18
A6: DevOps/Test | B6: Dockerfile | C6: 48
A7: DevOps/Test | B7: Powershell | C7: 257
A8: DevOps/Test | B8: Python | C8: 210
A9: DevOps/Test | B9: Rust | C9: 200478
A10: DevOps/Test | B10: Shell | C10: 933
A11: DevOps/Test | B11: TOML | C11: 2669
A12: DevOps/Test | B12: XML | C12: 33
A13: DevOps/Test | B13: YAML | C13: 597
A14: Excluded | B14: JSON | C14: 3801
A15: Excluded | B15: License | C15: 167
... A24: System | B24: WebGPU Shading Language | C24: 1136

Sheet Complex Files
A1: Top 15 most complex Rust files
A3: # | B3: File | C3: CC | D3: LOC | E3: Density
A4: 1 | B4: crates/ui-egui/src/canvas.rs | C4: 1434 | D4: 4666 | E4: 0.307
A5: 2 | B5: crates/ui-egui/src/panels.rs | C5: 896 | D5: 3368 | E5: 0.266
A6: 3 | B6: crates/engine/src/atn_cmds.rs | C6: 774 | D6: 2910 | E6: 0.266
A7: 4 | B7: crates/ui-egui/src/transform_tool.rs | C7: 652 | D7: 2434 | E7: 0.268
A8: 5 | B8: crates/ui-egui/src/type_tool.rs | C8: 566 | D8: 2369 | E8: 0.239
A9: 6 | B9: crates/compose/src/effects.rs | C9: 480 | D9: 1732 | E9: 0.277
A10: 7 | B10: crates/ui-egui/src/menus.rs | C10: 480 | D10: 1325 | E10: 0.362
A11: 8 | B11: crates/ui-egui/src/prefs_ui.rs | C11: 467 | D11: 1749 | E11: 0.267
A12: 9 | B12: crates/algo/src/inpaint.rs | C12: 435 | D12: 1625 | E12: 0.268
A13: 10 | B13: crates/ui-egui/src/vector_ui.rs | C13: 420 | D13: 1564 | E13: 0.269
A14: 11 | B14: crates/engine/src/layer_multi_cmds.rs | C14: 410 | D14: 1223 | E14: 0.335
A15: 12 | B15: crates/engine/src/channel_cmds.rs | C15: 398 | D15: 1615 | E15: 0.246
... A18: 15 | B18: crates/engine/src/vector_cmds.rs | C18: 371 | D18: 1703 | E18: 0.218

Sheet Clippy
A1: Clippy findings by lint (non-test code; pedantic + never-crash lints)
A3: Lint | B3: Count
A4: clippy::indexing_slicing | B4: 7765
A5: clippy::cast_possible_truncation | B5: 3483
A6: clippy::must_use_candidate | B6: 2441
A7: clippy::cast_precision_loss | B7: 2179
A8: clippy::many_single_char_names | B8: 1696
A9: clippy::cast_sign_loss | B9: 1639
A10: clippy::cast_possible_wrap | B10: 1079
A11: clippy::cast_lossless | B11: 793
A12: clippy::doc_markdown | B12: 632
A13: clippy::missing_errors_doc | B13: 595
A14: clippy::needless_raw_string_hashes | B14: 536
A15: clippy::redundant_closure_for_method_calls | B15: 238
... A76: clippy::comparison_chain | B76: 1
A77: Total | B77: =SUM(B4:B76) -> 25244

Sheet FP Transactions
A1: Transaction functions (EI / EQ / EO) from the command registry
A3: By type
A4: Type | B4: Count | C4: Rule
A5: EI | B5: 824 | C5: every state-changing command not matched below
A6: EQ | B6: 43 | C6: last segment info/list/get/inspect/printers/browse, *Info, list*
A7: EO | B7: 28 | C7: export, print, saveACopy, saveContents, presets/actions save, package, contactSheet, renderVideo, imageAssets
A9: By command prefix
A10: Command prefix | B10: EI | C10: EQ | D10: EO
A11: actions | B11: 14 | C11: 2 | D11: 1
A12: brush | B12: 11 | C12: 2 | D12: 1
A13: channel | B13: 15 | C13: 1 | D13: 0
A14: cloneSource | B14: 4 | C14: 1 | D14: 0
A15: color | B15: 1 | C15: 0 | D15: 0
A16: command | B16: 0 | C16: 1 | D16: 0
A17: count | B17: 7 | C17: 0 | D17: 0
A18: document | B18: 6 | C18: 4 | D18: 1
A19: edit | B19: 76 | C19: 1 | D19: 2
A20: file | B20: 32 | C20: 3 | D20: 17
A21: filter | B21: 122 | C21: 0 | D21: 0
A22: gradient | B22: 10 | C22: 2 | D22: 0
... A46: view | B46: 29 | C46: 1 | D46: 0

Sheet Function Points
A1: IFPUG function points (System)
A3: Function types
A4: Type | B4: Name | C4: Count | D4: Complexity | E4: Weight | F4: FP | G4: Basis
A5: EI | B5: External Input | C5: 824 | D5: average | E5: 4 | F5: 3296 | G5: state-changing engine commands from the registry (907 commands, 12 parameter-only variants collapsed); see fp-transactions.md
A6: EO | B6: External Output | C6: 28 | D6: average | E6: 5 | F6: 140 | G6: export, print, save-a-copy, preset/action save, package, contact sheet, render video, image assets; listed in fp-transactions.md
A7: EQ | B7: External Inquiry | C7: 43 | D7: average | E7: 4 | F7: 172 | G7: read-only registry commands (info / list / get / inspect / printers / browse); listed in fp-transactions.md
A8: ILF | B8: Internal Logical File | C8: 10 | D8: average | E8: 10 | F8: 100 | G8: logical files maintained: document (.pcraft incl. layers/channels/paths/history), preferences, shortcuts+workspaces, brush presets, swatches, gradients, patterns, layer styles, actions, tool/document/shape presets
A9: EIF | B9: External Interface File | C9: 11 | D9: average | E9: 7 | F9: 77 | G9: logical groups read from elsewhere: PSD/PSB, flat raster codecs, HDR (EXR/DPX), camera raw/DNG, HEIF, Affinity, Krita/OpenRaster, Photoshop preset files (ABR/ASE/ACO/GRD/PAT/ATN/ASL), ICC profiles, fonts, plug-ins
A10: UFP | F10: =SUM(F5:F9) -> 3785
A12: General System Characteristics
A13: # | B13: Characteristic | C13: DI (0-5) | D13: Justification
A14: 1 | B14: Data communications | C14: 2 | D14: Data communications: local TCP control channel and MCP over stdio; no network service
A15: 2 | B15: Distributed data processing | C15: 1 | D15: Distributed data processing: none beyond sandboxed in-process WASM plug-ins
A16: 3 | B16: Performance | C16: 4 | D16: Performance: explicit budgets (perf/budgets.toml), 24-36 MP targets, GPU compositor, nightly perf runs
A17: 4 | B17: Heavily used configuration | C17: 2 | D17: Heavily used configuration: runs on the user's own machine; varied GPUs handled by wgpu
A18: 5 | B18: Transaction rate | C18: 1 | D18: Transaction rate: single-user interactive editing
A19: 6 | B19: Online data entry | C19: 3 | D19: Online data entry: all editing is interactive (dialogs, tools, canvas)
A20: 7 | B20: End-user efficiency | C20: 4 | D20: End-user efficiency: Photoshop-parity menus, shortcuts, panels, command palette are a stated goal
A21: 8 | B21: Online update | C21: 3 | D21: Online update: interactive updates of the document ILF with undo and atomic saves
A22: 9 | B22: Complex processing | C22: 4 | D22: Complex processing: imaging algorithms, ICC colour management, compositing, type layout (rated 4, not 5)
A23: 10 | B23: Reusability | C23: 3 | D23: Reusability: psd, codecs, cms are designed as publishable standalone crates
A24: 11 | B24: Installation ease | C24: 3 | D24: Installation ease: signed installers for macOS, Windows, Linux, FreeBSD, plus a web build
A25: 12 | B25: Operational ease | C25: 2 | D25: Operational ease: autosave and recovery; no operator role
... A27: 14 | B27: Facilitate change | C27: 3 | D27: Facilitate change: data-driven command registry, preferences, actions/scripting
B28: ΣGSC | C28: 38
A30: IFPUG vs backfiring
A31: Method | B31: System FP
A32: IFPUG (AFP) | B32: 3899
A33: Backfiring (point) | B33: 3605
A34: Divergence | B34: -0.075
A35: Verdict (±30%) | B35: agree
A37: Subtotals and total
A38: Category | B38: Method | C38: FP | D38: Share
A39: System | B39: IFPUG AFP | C39: 3899 | D39: 0.575
A40: DevOps/Test | B40: backfired equivalent FP | C40: 2882 | D40: 0.425
A41: Total | C41: 6780 | D41: 1

Sheet Backfiring
A1: Capers Jones backfiring (LOC to FP)
A3: System
A4: Language | B4: Physical LOC | C4: LOC/FP | D4: FP (raw physical) | E4: FP (/ 1.3 physical->logical) | F4: Ratio source
A5: HTML | B5: 30 | C5: 40 | D5: 1 | E5: 1 | F5: analyst-assumed markup ratio
A6: Rust | B6: 256463 | C6: 55 | D6: 4663 | E6: 3587 | F6: analyst-assumed: no SPR/QSM ratio for Rust; nearest SPR peers C++ 55, Java 53
A7: TOML | B7: 8 | C7: 50 | D7: 0 | E7: 0 | F7: analyst-assumed for TOML/YAML/shell/PowerShell/Python/other build assets
A8: WebGPU Shading Language | B8: 1136 | C8: 50 | D8: 23 | E8: 17 | F8: analyst-assumed shader ratio
A9: System total | B9: =SUM(B5:B8) -> 257637 | D9: =SUM(D5:D8) -> 4687 | E9: =SUM(E5:E8) -> 3605
A11: DevOps/Test
A12: Language | B12: Physical LOC | C12: LOC/FP | D12: FP (raw physical) | E12: FP (/ 1.3 physical->logical) | F12: Ratio source
A13: Autoconf | B13: 309 | C13: 50 | D13: 6 | E13: 5 | F13: analyst-assumed for TOML/YAML/shell/PowerShell/Python/other build assets
A14: Docker ignore | B14: 18 | C14: 50 | D14: 0 | E14: 0 | F14: analyst-assumed for TOML/YAML/shell/PowerShell/Python/other build assets
A15: Dockerfile | B15: 48 | C15: 50 | D15: 1 | E15: 1 | F15: analyst-assumed for TOML/YAML/shell/PowerShell/Python/other build assets
A16: Powershell | B16: 257 | C16: 50 | D16: 5 | E16: 4 | F16: analyst-assumed for TOML/YAML/shell/PowerShell/Python/other build assets
A17: Python | B17: 210 | C17: 50 | D17: 4 | E17: 3 | F17: analyst-assumed for TOML/YAML/shell/PowerShell/Python/other build assets
A18: Rust | B18: 200478 | C18: 55 | D18: 3645 | E18: 2804 | F18: analyst-assumed: no SPR/QSM ratio for Rust; nearest SPR peers C++ 55, Java 53
A19: Shell | B19: 933 | C19: 50 | D19: 19 | E19: 14 | F19: analyst-assumed for TOML/YAML/shell/PowerShell/Python/other build assets
A20: TOML | B20: 2669 | C20: 50 | D20: 53 | E20: 41 | F20: analyst-assumed for TOML/YAML/shell/PowerShell/Python/other build assets
A21: XML | B21: 33 | C21: 50 | D21: 1 | E21: 1 | F21: analyst-assumed for TOML/YAML/shell/PowerShell/Python/other build assets
A22: YAML | B22: 597 | C22: 50 | D22: 12 | E22: 9 | F22: analyst-assumed for TOML/YAML/shell/PowerShell/Python/other build assets
A23: DevOps/Test total | B23: =SUM(B13:B22) -> 205552 | D23: 3747 | E23: =SUM(E13:E22) -> 2882

Sheet Cost
A1: Economic valuation: effort, cost, schedule
A2: Replacement cost, not market value. Salary figures are secondary citations; see README section 4.7.
A4: Salary inputs
A5: Source | B5: Annual base (USD) | C5: Note
A6: bls | B6: 133080 | C6: US BLS Occupational Outlook Handbook, software developers median annual wage May 2024 (cited via scaler.com; secondary sites report $135,980 for May 2025), accessed 2026-10-14
A7: payscale | B7: 98101 | C7: PayScale software engineer average base pay, self-reported (cited via scaler.com; not verified on payscale.com), accessed 2026-10-14
A8: salarycom | B8: 128709 | C8: Salary.com Software Engineer III US median, Oct 2025 (from a non-official mirror of the Salary.com page), accessed 2026-10-14
A10: Effort by productivity band
A11: FP/man-day | B11: ~FP/staff-month | C11: Level | D11: ~System LOC/man-day | E11: System man-months | F11: DevOps/Test man-months | G11: Total man-months (coding-centric)
A12: 0.32 | B12: 7 | C12: Jones full-lifecycle baseline (headline) | D12: 21 | E12: 554 | F12: n/a (in System) | G12: n/a (in System)
A13: 0.5 | B13: 11 | C13: below baseline (large / high-ceremony) | D13: 33 | E13: 354 | F13: 262 | G13: 616
A14: 1 | B14: 22 | C14: coding-centric / well-run | D14: 66 | E14: 177 | F14: 131 | G14: 308
A15: 2 | B15: 44 | C15: high-performing small team | D15: 132 | E15: 89 | F15: 65 | G15: 154
A16: 3 | B16: 66 | C16: elite / best-in-class | D16: 198 | E16: 59 | F16: 44 | G16: 103
A18: Cost by productivity band (fully loaded, burden 1.5x-1.75x)
A19: FP/man-day | B19: System (low) | C19: System (high) | D19: DevOps/Test (low) | E19: DevOps/Test (high) | F19: Total (coding-centric) (low) | G19: Total (coding-centric) (high)
A20: 0.32 | B20: 9046487 | C20: 10554235 | D20: n/a (in System) | F20: n/a (in System)
A21: 0.5 | B21: 5789752 | C21: 6754710 | D21: 4279995 | E21: 4993327 | F21: 10069746 | G21: 11748037
A22: 1 | B22: 2894876 | C22: 3377355 | D22: 2139997 | E22: 2496663 | F22: 5034873 | G22: 5874019
A23: 2 | B23: 1447438 | C23: 1688678 | D23: 1069999 | E23: 1248332 | F23: 2517437 | G23: 2937009
A24: 3 | B24: 964959 | C24: 1125785 | D24: 713332 | E24: 832221 | F24: 1678291 | G24: 1958006
A26: Schedule sanity check
A27: Quantity | B27: Value
A28: System FP | B28: 3899
A29: Exponent (mid-to-large commercial desktop product (Jones: ~0.4 mid-sized, ~0.45 large systems)) | B29: 0.42
A30: Calendar months = FP^exp | B30: 32.2
A31: Staff-months at 0.32 FP/day | B31: 554
A32: Implied average team | B32: 17.2

Sheet Test Pyramid
A1: Test pyramid
A3: Layer | B3: Suites | C3: Tests | D3: Share
A4: unit | B4: 111 | C4: 7550 | D4: 0.891
A5: integration | B5: 97 | C5: 745 | D5: 0.088
A6: acceptance | B6: 30 | C6: 177 | D6: 0.021
A7: Total | C7: =SUM(C4:C6) -> 8472

Sheet Test Suites
A1: Test-suite matrix (cargo test -- --list, default features)
A3: Package | B3: Suite | C3: Kind | D3: Tests | E3: of which #[ignore] | F3: Layer | G3: Deciding signal
A4: photocraft | B4: src/main.rs | C4: in-crate | D4: 128 | E4: 1 | F4: unit | G4: in-crate #[cfg(test)] modules
A5: photocraft | B5: tests/control_exit_code.rs | C5: test target | D5: 4 | E5: 0 | F5: acceptance | G5: spawns the built app binary (CARGO_BIN_EXE_)
A6: photocraft | B6: tests/startup_without_display.rs | C6: test target | D6: 2 | E6: 0 | F6: acceptance | G6: spawns the built app binary (CARGO_BIN_EXE_)
A7: photocraft-affinity | B7: src/lib.rs | C7: in-crate | D7: 20 | E7: 0 | F7: unit | G7: in-crate #[cfg(test)] modules
A8: photocraft-affinity | B8: tests/real_files.rs | C8: test target | D8: 2 | E8: 0 | F8: integration | G8: real-file corpus (corpus)
A9: photocraft-algo | B9: src/lib.rs | C9: in-crate | D9: 570 | E9: 22 | F9: unit | G9: in-crate #[cfg(test)] modules
A10: photocraft-algo | B10: tests/retouch_blur_exact.rs | C10: test target | D10: 2 | E10: 0 | F10: unit | G10: pure in-memory API calls (no I/O, GPU or process signal)
A11: photocraft-automation | B11: src/lib.rs | C11: in-crate | D11: 68 | E11: 0 | F11: unit | G11: in-crate #[cfg(test)] modules
A12: photocraft-automation | B12: tests/agent_tasks.rs | C12: test target | D12: 5 | E12: 0 | F12: integration | G12: filesystem I/O (std::fs)
A13: photocraft-automation | B13: tests/agent_tasks_more.rs | C13: test target | D13: 1 | E13: 0 | F13: integration | G13: filesystem I/O (std::fs)
A14: photocraft-automation | B14: tests/bridge.rs | C14: test target | D14: 3 | E14: 0 | F14: acceptance | G14: drives the TCP control channel (TcpStream)
A15: photocraft-automation | B15: tests/inactive_save.rs | C15: test target | D15: 1 | E15: 0 | F15: integration | G15: filesystem I/O (std::fs)
... A241: xtask | B241: src/main.rs | C241: in-crate | D241: 61 | E241: 0 | F241: unit | G241: in-crate #[cfg(test)] modules

Sheet Tools
A1: Tools and versions
A3: Tool | B3: Version | C3: Obtained by
A4: scc | B4: 3.5.0 | C4: go install github.com/boyter/scc/v3@v3.5.0
A5: rustc / clippy | B5: 1.97.0 / 0.1.97 | C5: rustup toolchain in the container
A6: PlantUML | B6: 1.2025.4 (bundled C4 stdlib) | C6: release jar, run with the preinstalled JRE
A7: Graphviz | B7: 2.43.0 | C7: apt-get install graphviz
A8: metrics, testlist, fpcount, sizing | B8: skill helpers | C8: std-only Rust, compiled with rustc by scripts/setup-tools.sh

Sheet Diagram Logical
A1: Logical view
A2: Source: codebase-audit-report/images/01-logical.png

Sheet Diagram Runtime
A1: Runtime view
A2: Source: codebase-audit-report/images/02-runtime.png

Sheet Diagram Dependencies
A1: Dependencies view
A2: Source: codebase-audit-report/images/03-dependencies.png

Sheet Diagram Testing
A1: Testing view
A2: Source: codebase-audit-report/images/04-testing.png

Sheet Diagram Deploy
A1: Deploy view
A2: Source: codebase-audit-report/images/05-deploy.png

Sheet Diagram Logical Annotated
A1: Logical Annotated view
A2: Source: codebase-audit-report/images/01-logical-annotated.png
